tlc59711/__init__.py
tlc59711/tlc59711.py
rpi_tlc59711-1.0.0.dist-info/METADATA
rpi_tlc59711-1.0.0.dist-info/WHEEL
rpi_tlc59711-1.0.0.dist-info/top_level.txt
rpi_tlc59711-1.0.0.dist-info/RECORD
