Metadata-Version: 2.1
Name: rpi-tlc59711
Version: 1.0.0
Summary: Raspberry Pi library to communicate with the TLC59711 12 channel LED driver
Home-page: https://github.com/Liriel/tlc59711
Author: Lassi
Author-email: lassi@heisl.org
License: BSD
Platform: UNKNOWN
Classifier: Development Status :: 3 - Alpha
Classifier: Intended Audience :: Developers
Classifier: Topic :: Software Development :: Libraries
Classifier: Topic :: System :: Hardware
Classifier: License :: OSI Approved :: BSD License
Classifier: Programming Language :: Python :: 3
Classifier: Programming Language :: Python :: 2.7
